elgato/__init__.py
elgato/__main__.py
PyElgato-1.2.0.dist-info/LICENSE
PyElgato-1.2.0.dist-info/METADATA
PyElgato-1.2.0.dist-info/WHEEL
PyElgato-1.2.0.dist-info/entry_points.txt
PyElgato-1.2.0.dist-info/top_level.txt
PyElgato-1.2.0.dist-info/RECORD
