Metadata-Version: 2.1
Name: PyElgato
Version: 1.2.0
Summary: Control script for El Gato brand keylights
Home-page: https://github.com/waxlamp/elgato
Author: Roni Choudhury
Author-email: aichoudh@gmail.com
License: LICENSE
Platform: UNKNOWN
Requires-Dist: leglight (==0.2.0)
